[
  {
    "place": 1,
    "name": ".k..",
    "author": "...",
    "id": "...",
    "chance": "Verified by ...",
    "youtube": "abcd1234",
    "gif": "https://media0.giphy.com/media/.../giphy.gif",
    "wrName": "Verification video",
    "wrLink": "https://youtube.com/watch?v=example2",
    "points": 0,
    "victors": []
  },
  {
    "place": 2,
    "name": "...",
    "author": "...",
    "id": "...",
    "chance": "Verified by ...",
    "youtube": "abcd1234",
    "gif": "https://media0.giphy.com/media/.../giphy.gif",
    "wrName": "Verification video",
    "wrLink": "https://youtube.com/watch?v=example2",
    "points": 0,
    "victors": []
  },
  {
    "place": 3,
    "name": "...",
    "author": "...",
    "id": "...",
    "chance": "Verified by ...",
    "youtube": "abcd1234",
    "gif": "https://media0.giphy.com/media/.../giphy.gif",
    "wrName": "Verification video",
    "wrLink": "https://youtube.com/watch?v=example",
    "points": 0,
    "victors": []
  }
]
